README.md
setup.py
ffmpeg_gpt/__init__.py
ffmpeg_gpt/ffmpeg_gpt.py
ffmpeg_gpt/utils.py
ffmpeg_gpt.egg-info/PKG-INFO
ffmpeg_gpt.egg-info/SOURCES.txt
ffmpeg_gpt.egg-info/dependency_links.txt
ffmpeg_gpt.egg-info/entry_points.txt
ffmpeg_gpt.egg-info/requires.txt
ffmpeg_gpt.egg-info/top_level.txt