Metadata-Version: 2.1
Name: ffmpeg-gpt
Version: 0.1.1
Summary: Use GPT to generate ffmpeg commands
Home-page: https://github.com/apirrone/ffmpeg_gpt
Author: Antoine Pirrone
Author-email: antoine.pirrone@gmail.com
License: UNKNOWN
Platform: UNKNOWN
